aletheia/base/__init__.py
aletheia/base/classes/__init__.py
aletheia/base/classes/itarget.py
aletheia/base/exceptions/__init__.py
aletheia/base/exceptions/base.py
aletheia/base/exceptions/immutable_property_exception.py
aletheia/base/exceptions/property_not_found_exception.py
aletheia/base/exceptions/template_already_loaded_exception.py
aletheia_base-0.0.1.dist-info/METADATA
aletheia_base-0.0.1.dist-info/WHEEL
aletheia_base-0.0.1.dist-info/RECORD
